<Alloy>
	<Window class="container">
		<View class="header">
			<View class="headerContent">
				<View id="backButton">
					<ImageView class="backButtonImage" image="../../back@2x.png"></ImageView>
					<Label class="addView">Games</Label>
				</View>
				<Label class="white" id="title">Play</Label>
			</View>
		</View>
		<View id="main" class="create">
			<!-- <WebView id="webviewproxy"></WebView> -->
		</View>
		<View class="submitContainer">
			<Button id="submit" class="submit" title="Add Photo" />
		</View>
	</Window>
</Alloy>